evee/__init__.py
evee/abstract_event_dispatcher.py
evee/abstract_event_subscriber.py
evee/event.py
evee/event_dispatcher.py
evee/exception.py
evee/generic_event.py
evee/immutable_event_dispatcher.py
evee/__pycache__/__init__.cpython-36.pyc
evee/__pycache__/abstract_event_dispatcher.cpython-36.pyc
evee/__pycache__/abstract_event_subscriber.cpython-36.pyc
evee/__pycache__/event.cpython-36.pyc
evee/__pycache__/event_dispatcher.cpython-36.pyc
evee-0.2.0.dist-info/DESCRIPTION.rst
evee-0.2.0.dist-info/METADATA
evee-0.2.0.dist-info/RECORD
evee-0.2.0.dist-info/WHEEL
evee-0.2.0.dist-info/metadata.json
evee-0.2.0.dist-info/top_level.txt
evee-0.2.0.dist-info/zip-safe
