Metadata-Version: 2.0
Name: evee
Version: 0.2.0
Summary: Evee is an event dispatcher port of the Symfony Event Dispatcher Component. It allows your applications to communicate with one another by dispatching and listening for events.
Home-page: https://github.com/onema/evee
Author: Juan Manuel Torres
Author-email: software@onema.io
License: MIT
Download-URL: https://github.com/onema/evee/archive/v0.2.0.tar.gz
Platform: UNKNOWN
Classifier: Intended Audience :: Developers
Classifier: Operating System :: OS Independent
Classifier: Programming Language :: Python
Classifier: Topic :: Software Development :: Libraries :: Python Modules
